checkmarks/__init__.py
checkmarks/cli.py
checkmarks-0.1.0.dist-info/licenses/LICENSE
checkmarks-0.1.0.dist-info/METADATA
checkmarks-0.1.0.dist-info/WHEEL
checkmarks-0.1.0.dist-info/entry_points.txt
checkmarks-0.1.0.dist-info/top_level.txt
checkmarks-0.1.0.dist-info/RECORD
