Metadata-Version: 2.4
Name: checkmarks
Version: 0.1.0
Summary: A simple CLI for tracking progress with markdown checklists
Author-email: menisadi <menisadi@gmail.com>
License: MIT License
Keywords: cli,markdown,checklists
License-File: LICENSE
Dynamic: license-file
